cpskin.contenttypes-1.0.13-py2.7-nspkg.pth
cpskin/contenttypes/__init__.py
cpskin/contenttypes/configure.zcml
cpskin/contenttypes/interfaces.py
cpskin/contenttypes/permissions.zcml
cpskin/contenttypes/profiles.zcml
cpskin/contenttypes/setuphandlers.py
cpskin/contenttypes/testing.py
cpskin/contenttypes/upgradehandlers.py
cpskin/contenttypes/validator.py
cpskin/contenttypes/browser/__init__.py
cpskin/contenttypes/browser/configure.zcml
cpskin/contenttypes/browser/procedure.py
cpskin/contenttypes/browser/product.py
cpskin/contenttypes/browser/resources/procedure.png
cpskin/contenttypes/browser/resources/product.png
cpskin/contenttypes/browser/templates/procedure.pt
cpskin/contenttypes/browser/templates/product.pt
cpskin/contenttypes/content/__init__.py
cpskin/contenttypes/content/procedure.py
cpskin/contenttypes/content/product.py
cpskin/contenttypes/profiles/default/browserlayer.xml
cpskin/contenttypes/profiles/default/metadata.xml
cpskin/contenttypes/profiles/default/rolemap.xml
cpskin/contenttypes/profiles/default/types.xml
cpskin/contenttypes/profiles/default/types/Procedure.xml
cpskin/contenttypes/profiles/default/types/Product.xml
cpskin/contenttypes/tests/__init__.py
cpskin/contenttypes/tests/test_ct_product.py
cpskin/contenttypes/tests/test_setup.py
cpskin.contenttypes-1.0.13.dist-info/DESCRIPTION.rst
cpskin.contenttypes-1.0.13.dist-info/METADATA
cpskin.contenttypes-1.0.13.dist-info/RECORD
cpskin.contenttypes-1.0.13.dist-info/WHEEL
cpskin.contenttypes-1.0.13.dist-info/entry_points.txt
cpskin.contenttypes-1.0.13.dist-info/metadata.json
cpskin.contenttypes-1.0.13.dist-info/namespace_packages.txt
cpskin.contenttypes-1.0.13.dist-info/top_level.txt
