Metadata-Version: 2.0
Name: cpskin.contenttypes
Version: 1.0.13
Summary: CPSkin content types
Home-page: https://pypi.python.org/pypi/cpskin.contenttypes
Author: Laurent Lasudry
Author-email: laurent.lasudry@affinitic.be
License: GPL version 2
Keywords: Python Plone
Platform: UNKNOWN
Classifier: Environment :: Web Environment
Classifier: Framework :: Plone
Classifier: Framework :: Plone :: 4.3
Classifier: Programming Language :: Python
Classifier: Programming Language :: Python :: 2.7
Classifier: Operating System :: OS Independent
Classifier: License :: OSI Approved :: GNU General Public License v2 (GPLv2)
Provides-Extra: test
Requires-Dist: plone.app.dexterity
Requires-Dist: plone.api (>=1.8.4)
Requires-Dist: Products.GenericSetup (>=1.8.2)
Requires-Dist: setuptools
Requires-Dist: plone.app.dexterity (<=2.1.1)
Requires-Dist: plone.app.referenceablebehavior
Requires-Dist: plone.app.relationfield
Requires-Dist: plone.app.lockingbehavior
Requires-Dist: plone.schema
Requires-Dist: plone.app.contenttypes
Requires-Dist: plone.app.imagecropping
Requires-Dist: cpskin.locales
Requires-Dist: unidecode
Requires-Dist: imio.behavior.teleservices
Provides-Extra: test
Requires-Dist: plone.app.robotframework; extra == 'test'
